ud_compatibility/UD-UniMorph.tsv
ud_compatibility/__init__.py
ud_compatibility/languages.py
ud_compatibility/marry.py
ud_compatibility/paths.py
ud_compatibility/translator.py
ud_compatibility/um_reader.py
ud_compatibility/utils.py
ud_compatibility-0.1.2.dist-info/LICENSE
ud_compatibility-0.1.2.dist-info/WHEEL
ud_compatibility-0.1.2.dist-info/METADATA
ud_compatibility-0.1.2.dist-info/RECORD
