Metadata-Version: 2.1
Name: ud-compatibility
Version: 0.1.2
Summary: Converts conllu files with features that use the Universal Dependency (UD) annotation schema to features that use the Universal Morphology (UM) schema.
Author-email: Arya McCarthy <arya@jhu.edu>
Maintainer-email: Daniel Yakubov <daniel.yakubov23@gmail.com>
Requires-Python: >=3.5
Requires-Dist: termcolor == 2.3.0
